Metadata-Version: 1.1
Name: multiple-wave
Version: 0.0.2
Summary: A Covid model
Home-page: UNKNOWN
Author: Krishna Harsha
Author-email: <khkrishnaharsha123@gmail.com>
License: UNKNOWN
Keywords: python,covid,multiple waves,second wave,gaussian
Platform: UNKNOWN
Classifier: Development Status :: 3 - Alpha
Classifier: Intended Audience :: Education
Classifier: License :: OSI Approved :: MIT License
Classifier: Programming Language :: Python :: 3
Classifier: Operating System :: Microsoft :: Windows
